destructfolder/destructfolder.py
destructfolder/opencv_util.py
destructfolder/path_util.py
destructfolder-0.0.1.dist-info/METADATA
destructfolder-0.0.1.dist-info/WHEEL
destructfolder-0.0.1.dist-info/top_level.txt
destructfolder-0.0.1.dist-info/RECORD
