Metadata-Version: 2.1
Name: destructfolder
Version: 0.0.1
Summary: A library for destructing folders content for data like txt, image, npy
Author: CWKSC
Project-URL: Homepage, https://github.com/cwksc/DestructFolder
Keywords: destruct,folder
Requires-Python: <=3.8,>=3.7
Requires-Dist: torch
Requires-Dist: torchvision
Requires-Dist: torchaudio
Requires-Dist: numpy
Requires-Dist: opencv-contrib-python
Requires-Dist: tqdm
Provides-Extra: dev
Requires-Dist: black ; extra == 'dev'
Requires-Dist: pytest ; extra == 'dev'
